asiakirjasuodatin/__init__.py
asiakirjasuodatin/__main__.py
asiakirjasuodatin/api.py
asiakirjasuodatin/cli.py
asiakirjasuodatin-2023.6.24.dist-info/LICENSE
asiakirjasuodatin-2023.6.24.dist-info/METADATA
asiakirjasuodatin-2023.6.24.dist-info/WHEEL
asiakirjasuodatin-2023.6.24.dist-info/entry_points.txt
asiakirjasuodatin-2023.6.24.dist-info/top_level.txt
asiakirjasuodatin-2023.6.24.dist-info/RECORD
