Metadata-Version: 2.1
Name: asiakirjasuodatin
Version: 2023.6.24
Summary: Document filter (Finnish: asiakirjasuodatin) that read a JSON serialization of the Pandoc AST from stdin, transform it in some way, and write it to stdout.
Author-email: Stefan Hagen <stefan@hagen.link>
Maintainer-email: Stefan Hagen <stefan@hagen.link>
Project-URL: Homepage, https://git.sr.ht/~sthagen/asiakirjasuodatin
Project-URL: Bug-Tracker, https://todo.sr.ht/~sthagen/asiakirjasuodatin
Project-URL: Documentation, https://codes.dilettant.life/docs/asiakirjasuodatin
Project-URL: Source-Code, https://git.sr.ht/~sthagen/asiakirjasuodatin
Project-URL: Test-Coverage, https://codes.dilettant.life/coverage/asiakirjasuodatin
Keywords: developer-tools,devops
Classifier: Development Status :: 3 - Alpha
Classifier: Intended Audience :: Developers
Classifier: License :: OSI Approved :: MIT License
Classifier: Programming Language :: Python :: 3.10
Classifier: Programming Language :: Python :: 3.10
Classifier: Programming Language :: Python :: 3.12
Classifier: Programming Language :: Python :: 3.9
Requires-Python: >=3.9
License-File: LICENSE
Requires-Dist: msgspec (>=0.16.0)
Requires-Dist: pandocfilters (>=1.5.0)
Provides-Extra: dev
Requires-Dist: black ; extra == 'dev'
Requires-Dist: coverage ; extra == 'dev'
Requires-Dist: hypothesis ; extra == 'dev'
Requires-Dist: mypy ; extra == 'dev'
Requires-Dist: pytest ; extra == 'dev'
Requires-Dist: pytest-cov ; extra == 'dev'
Requires-Dist: pytest-flake8 ; extra == 'dev'
Requires-Dist: ruff ; extra == 'dev'
